emotion_machine/__init__.py
emotion_machine/behaviors.py
emotion_machine/client.py
emotion_machine/exceptions.py
emotion_machine/relationship.py
emotion_machine/streaming.py
emotion_machine/websocket.py
emotion_machine-2.0.5.dist-info/METADATA
emotion_machine-2.0.5.dist-info/WHEEL
emotion_machine-2.0.5.dist-info/licenses/LICENSE
emotion_machine-2.0.5.dist-info/RECORD
