Metadata-Version: 2.4
Name: emotion-machine
Version: 2.0.5
Summary: SDK for building AI companions with persistent relationships
Author: Emotion Machine
License: MIT
License-File: LICENSE
Classifier: Framework :: AsyncIO
Classifier: Programming Language :: Python :: 3
Classifier: Programming Language :: Python :: 3.10
Classifier: Programming Language :: Python :: 3.11
Classifier: Programming Language :: Python :: 3.12
Classifier: Typing :: Typed
Requires-Python: >=3.10
Requires-Dist: cron-validator>=1.0.8
Requires-Dist: httpx>=0.27.0
Requires-Dist: websockets>=12.0
